{"statsModo":[{"modo":"Bus","modoNombre":"Bus","n_viajes":5,"porcentaje":55.6,"velocidad_promedio":30.3,"tiempo_promedio_min":72,"distancia_promedio_km":27.31},{"modo":"Auto","modoNombre":"Auto","n_viajes":2,"porcentaje":22.2,"velocidad_promedio":35.8,"tiempo_promedio_min":75,"distancia_promedio_km":28.31},{"modo":"No Motorizado","modoNombre":"No Motorizado","n_viajes":1,"porcentaje":11.1,"velocidad_promedio":18.7,"tiempo_promedio_min":90,"distancia_promedio_km":28.06},{"modo":"Metro/Tren","modoNombre":"Metro/Tren","n_viajes":1,"porcentaje":11.1,"velocidad_promedio":55.3,"tiempo_promedio_min":30,"distancia_promedio_km":27.65}],"total":9,"initialStatsMap":{"Bus":55.6,"Auto":22.2,"No Motorizado":11.1,"Metro/Tren":11.1}}