{"statsModo":[{"modo":"No Motorizado","modoNombre":"No Motorizado","n_viajes":21,"porcentaje":48.8,"velocidad_promedio":14.8,"tiempo_promedio_min":103.8,"distancia_promedio_km":23.2},{"modo":"Auto","modoNombre":"Auto","n_viajes":15,"porcentaje":34.9,"velocidad_promedio":24.2,"tiempo_promedio_min":75.5,"distancia_promedio_km":24.93},{"modo":"Bus","modoNombre":"Bus","n_viajes":6,"porcentaje":14,"velocidad_promedio":11,"tiempo_promedio_min":135,"distancia_promedio_km":23.24},{"modo":"Metro/Tren","modoNombre":"Metro/Tren","n_viajes":1,"porcentaje":2.3,"velocidad_promedio":16.6,"tiempo_promedio_min":90,"distancia_promedio_km":24.86}],"total":43,"initialStatsMap":{"No Motorizado":48.8,"Auto":34.9,"Bus":14,"Metro/Tren":2.3}}