{"statsModo":[{"modo":"Bus","modoNombre":"Bus","n_viajes":10,"porcentaje":47.6,"velocidad_promedio":6.9,"tiempo_promedio_min":52.7,"distancia_promedio_km":5.78},{"modo":"No Motorizado","modoNombre":"No Motorizado","n_viajes":8,"porcentaje":38.1,"velocidad_promedio":6.2,"tiempo_promedio_min":59.4,"distancia_promedio_km":5.98},{"modo":"Auto","modoNombre":"Auto","n_viajes":3,"porcentaje":14.3,"velocidad_promedio":13.9,"tiempo_promedio_min":26.7,"distancia_promedio_km":6.35}],"total":21,"initialStatsMap":{"Bus":47.6,"No Motorizado":38.1,"Auto":14.3}}
